mukham/__init__.py
mukham/__main__.py
mukham/detector.py
mukham/models/deploy.prototxt
mukham/models/res10_300x300_ssd_iter_140000.caffemodel
mukham/tests/__init__.py
mukham/tests/test.py
mukham/tests/data/faces/bryant_daughter.jpg
mukham/tests/data/images/bryant_daughter.jpg
mukham/tests/data/images/kobe_large.jpg
mukham-1.0.9.dist-info/LICENSE
mukham-1.0.9.dist-info/METADATA
mukham-1.0.9.dist-info/WHEEL
mukham-1.0.9.dist-info/top_level.txt
mukham-1.0.9.dist-info/RECORD
