Metadata-Version: 2.1
Name: mukham
Version: 1.0.9
Summary: A basic library to crop largest face from the images.
Home-page: https://github.com/akvallapuram/mukham
Author: Anish Krishna Vallapuram
Author-email: akvallapuram@connect.ust.hk
License: UNKNOWN
Platform: UNKNOWN
Classifier: Programming Language :: Python :: 3
Classifier: License :: OSI Approved :: MIT License
Classifier: Operating System :: OS Independent
Requires-Python: >=3.7
Requires-Dist: numpy (>=1.18.1)
Requires-Dist: opencv-python (>=4.1.2.30)
